__main__.py
main.py
templates/__init__.py
templates/functions.py
templates/imports.py
templates/utils.py
neurostage-1.0.dist-info/LICENSE.md
neurostage-1.0.dist-info/METADATA
neurostage-1.0.dist-info/WHEEL
neurostage-1.0.dist-info/entry_points.txt
neurostage-1.0.dist-info/top_level.txt
neurostage-1.0.dist-info/RECORD
