Metadata-Version: 2.2
Name: neurostage
Version: 1.0
Summary: A framework for managing deep learning projects
Home-page: https://github.com/catalina-delgado/NeuroStage
Author: Catalina Delgado
Author-email: catalina08delgado@gmail.com
Keywords: training,deepLearning,framework
Classifier: Programming Language :: Python :: 3
Classifier: License :: OSI Approved :: MIT License
Classifier: Operating System :: OS Independent
Requires-Python: >=3.6
License-File: LICENSE.md
Requires-Dist: numpy>=1.21.0
Requires-Dist: tensorflow>=2.10.0
Requires-Dist: opencv-python>=4.5.0
Requires-Dist: pandas>=1.3.0
Dynamic: author
Dynamic: author-email
Dynamic: classifier
Dynamic: description
Dynamic: description-content-type
Dynamic: home-page
Dynamic: keywords
Dynamic: requires-dist
Dynamic: requires-python
Dynamic: summary
